low_comm_tools/__init__.py
low_comm_tools/_version.py
low_comm_tools/_version.pyi
low_comm_tools/add_subtable.py
low_comm_tools/beam_model.py
low_comm_tools/delay_table_to_txt.py
low_comm_tools/exceptions.py
low_comm_tools/get_field_name.py
low_comm_tools/gleam_model.py
low_comm_tools/log_config.py
low_comm_tools/ms_utils.py
low_comm_tools/options.py
low_comm_tools/py.typed
low_comm_tools/rename_telescope.py
low_comm_tools/stations.py
low_comm_tools/vis_rotate.py
low_comm_tools/data/__init__.py
low_comm_tools/data/ska_low_angles_degrees.json
low_comm_tools/data/tests/__init__.py
low_comm_tools/plotting/__init__.py
low_comm_tools/plotting/ao_calibrate.py
low_comm_tools/plotting/baselines.py
low_comm_tools/plotting/sdp_calibrate.py
low_comm_tools/sdp/__init__.py
low_comm_tools/sdp/inst_mitch.py
low_comm_tools/sdp/utils.py
ska_ssc_low_comm_tools-1.2.0.data/scripts/low_bandpass_cal
ska_ssc_low_comm_tools-1.2.0.data/scripts/low_casa_applycal
ska_ssc_low_comm_tools-1.2.0.data/scripts/low_casa_average
ska_ssc_low_comm_tools-1.2.0.data/scripts/low_casa_listobs
ska_ssc_low_comm_tools-1.2.0.data/scripts/low_casa_preprocess
ska_ssc_low_comm_tools-1.2.0.data/scripts/low_casa_print_field
ska_ssc_low_comm_tools-1.2.0.dist-info/METADATA
ska_ssc_low_comm_tools-1.2.0.dist-info/WHEEL
ska_ssc_low_comm_tools-1.2.0.dist-info/entry_points.txt
ska_ssc_low_comm_tools-1.2.0.dist-info/licenses/LICENSE
ska_ssc_low_comm_tools-1.2.0.dist-info/RECORD
