Metadata-Version: 2.4
Name: ska-ssc-low-comm-tools
Version: 1.2.0
Summary: SKA-Low Commissioning Tools
Project-URL: Homepage, https://gitlab.com/ska-telescope/ssc/ska-low-scicomm-tools
Project-URL: Bug Tracker, https://gitlab.com/ska-telescope/ssc/ska-low-scicomm-tools/issues
Project-URL: Discussions, https://gitlab.com/ska-telescope/ssc/ska-low-scicomm-tools/discussions
Project-URL: Changelog, https://gitlab.com/ska-telescope/ssc/ska-low-scicomm-tools/releases
Author-email: SKA-Low Commissioning Team <alec.thomson@skao.int>
License-Expression: BSD-3-Clause
License-File: LICENSE
Classifier: Development Status :: 1 - Planning
Classifier: Intended Audience :: Developers
Classifier: Intended Audience :: Science/Research
Classifier: Operating System :: OS Independent
Classifier: Programming Language :: Python
Classifier: Programming Language :: Python :: 3
Classifier: Programming Language :: Python :: 3 :: Only
Classifier: Programming Language :: Python :: 3.10
Classifier: Programming Language :: Python :: 3.11
Classifier: Programming Language :: Python :: 3.12
Classifier: Programming Language :: Python :: 3.13
Classifier: Topic :: Scientific/Engineering
Classifier: Typing :: Typed
Requires-Python: >=3.11
Requires-Dist: astropy>=6.1.7
Requires-Dist: astroquery>=0.4.10
Requires-Dist: everybeam>=0.7.2
Requires-Dist: healpy>=1.18.1
Requires-Dist: matplotlib>=3.10.6
Requires-Dist: numpy>=1.26.4
Requires-Dist: pandas>=2.3.2
Requires-Dist: polars>=1.33.1
Requires-Dist: pydantic>=2.11.9
Requires-Dist: python-casacore>=3.7.1
Requires-Dist: radio-beam>=0.3.9
Requires-Dist: rm-lite>=2025.5.1
Requires-Dist: ska-low-mccs-calibration>=1.2.0
Requires-Dist: ska-sdp-datamodels>=1.0.1
Requires-Dist: ska-sdp-func-python>=1.0.1
Requires-Dist: ska-sdp-func>=1.2.2
Requires-Dist: ska-sdp-instrumental-calibration[python-casacore,ska-sdp-func]>=0.4.1
Requires-Dist: tqdm>=4.67.1
Provides-Extra: dev
Requires-Dist: mypy>=1.17.1; extra == 'dev'
Requires-Dist: nox>=2025.5.1; extra == 'dev'
Requires-Dist: pre-commit>=4.3.0; extra == 'dev'
Requires-Dist: pytest-cov>=6.2.1; extra == 'dev'
Requires-Dist: pytest>=8.4.1; extra == 'dev'
Requires-Dist: ruff>=0.12.11; extra == 'dev'
Requires-Dist: types-tqdm>=4.67.0.20250809; extra == 'dev'
Provides-Extra: docs
Requires-Dist: furo>=2023.08.17; extra == 'docs'
Requires-Dist: myst-parser>=0.13; extra == 'docs'
Requires-Dist: ska-ser-sphinx-theme; extra == 'docs'
Requires-Dist: sphinx-argparse; extra == 'docs'
Requires-Dist: sphinx-autoapi; extra == 'docs'
Requires-Dist: sphinx-autodoc-typehints; extra == 'docs'
Requires-Dist: sphinx-copybutton; extra == 'docs'
Requires-Dist: sphinx>=7.0; extra == 'docs'
